dataloopsdk/__init__.py
dataloopsdk/sdk.py
dataloopsdk/types.py
dataloopsdk-0.8.dist-info/METADATA
dataloopsdk-0.8.dist-info/WHEEL
dataloopsdk-0.8.dist-info/top_level.txt
dataloopsdk-0.8.dist-info/RECORD
